{"stats":{"minecraft:killed_by":{"minecraft:skeleton":2,"minecraft:vindicator":1,"minecraft:creeper":1,"minecraft:enderman":2,"minecraft:iron_golem":1},"minecraft:mined":{"minecraft:torch":8,"minecraft:comparator":3,"minecraft:cherry_log":1,"minecraft:lever":1,"minecraft:lava_cauldron":1,"minecraft:nether_quartz_ore":44,"minecraft:chest":6,"minecraft:pumpkin":1,"minecraft:polished_blackstone_brick_stairs":1,"minecraft:netherrack":2710,"minecraft:carrots":3,"minecraft:spruce_sapling":29,"minecraft:lectern":1,"minecraft:gravel":30,"minecraft:short_grass":39,"minecraft:weeping_vines":3,"minecraft:amethyst_block":32,"minecraft:weeping_vines_plant":6,"minecraft:brown_mushroom":18,"minecraft:crafter":4,"minecraft:crafting_table":1,"minecraft:deepslate_redstone_ore":98,"minecraft:sweet_berry_bush":7,"minecraft:magma_block":44,"minecraft:obsidian":11,"minecraft:redstone_torch":4,"minecraft:copper_ore":80,"minecraft:grindstone":4,"minecraft:nether_wart_block":2,"minecraft:andesite":4,"minecraft:repeater":10,"minecraft:blast_furnace":24,"minecraft:deepslate_gold_ore":84,"minecraft:gold_block":1,"minecraft:budding_amethyst":4,"minecraft:wall_torch":5,"minecraft:fern":1,"minecraft:deepslate_diamond_ore":112,"minecraft:cauldron":1,"minecraft:deepslate_lapis_ore":10,"minecraft:deepslate_iron_ore":8,"minecraft:birch_planks":2,"minecraft:amethyst_cluster":2,"minecraft:iron_ore":12,"minecraft:stone":164,"minecraft:glass_pane":1,"minecraft:podzol":6,"minecraft:glass":8,"minecraft:coal_ore":54,"minecraft:diorite":6,"minecraft:wheat":27,"minecraft:ancient_debris":1,"minecraft:oak_planks":37,"minecraft:white_bed":2,"minecraft:cherry_leaves":11,"minecraft:brewing_stand":2,"minecraft:fletching_table":6,"minecraft:bookshelf":12,"minecraft:crimson_roots":16,"minecraft:crimson_nylium":141,"minecraft:glow_lichen":1,"minecraft:dark_oak_fence":4,"minecraft:crying_obsidian":2,"minecraft:tall_grass":4,"minecraft:polished_blackstone_bricks":1,"minecraft:rail":43,"minecraft:crimson_stairs":2,"minecraft:oak_stairs":44,"minecraft:dirt":29,"minecraft:hopper":7,"minecraft:grass_block":34,"minecraft:spruce_leaves":72,"minecraft:carved_pumpkin":9,"minecraft:tuff":66,"minecraft:spruce_door":1,"minecraft:nether_gold_ore":32,"minecraft:deepslate":497,"minecraft:sand":100,"minecraft:calcite":3,"minecraft:cherry_planks":1,"minecraft:cherry_slab":1,"minecraft:redstone_wire":21,"minecraft:lapis_ore":8},"minecraft:custom":{"minecraft:time_since_rest":2532,"minecraft:talked_to_villager":407,"minecraft:leave_game":14,"minecraft:damage_taken":6521,"minecraft:mob_kills":281,"minecraft:boat_one_cm":88855,"minecraft:time_since_death":203816,"minecraft:interact_with_brewingstand":3,"minecraft:interact_with_furnace":56,"minecraft:sleep_in_bed":24,"minecraft:inspect_dispenser":13,"minecraft:swim_one_cm":63725,"minecraft:total_world_time":565777,"minecraft:crouch_one_cm":195958,"minecraft:climb_one_cm":9453,"minecraft:deaths":8,"minecraft:animals_bred":9,"minecraft:traded_with_villager":1207,"minecraft:interact_with_crafting_table":69,"minecraft:walk_one_cm":943250,"minecraft:walk_under_water_one_cm":18036,"minecraft:damage_dealt":42963,"minecraft:play_time":565777,"minecraft:jump":9000,"minecraft:drop":134,"minecraft:use_cauldron":3,"minecraft:open_barrel":36,"minecraft:sprint_one_cm":1359673,"minecraft:open_chest":472,"minecraft:inspect_hopper":23,"minecraft:fall_one_cm":158046,"minecraft:fly_one_cm":1777255,"minecraft:interact_with_anvil":37,"minecraft:walk_on_water_one_cm":114307,"minecraft:sneak_time":118164,"minecraft:raid_trigger":1,"minecraft:interact_with_blast_furnace":2,"minecraft:interact_with_grindstone":8},"minecraft:dropped":{"minecraft:rotten_flesh":9,"minecraft:iron_chestplate":1,"minecraft:pumpkin_seeds":4,"minecraft:lead":3,"minecraft:crimson_roots":6,"minecraft:gravel":19,"minecraft:bone":1,"minecraft:glass":4,"minecraft:dirt":70,"minecraft:poppy":4,"minecraft:glowstone":50,"minecraft:stone":5,"minecraft:wheat_seeds":7,"minecraft:ominous_bottle":1,"minecraft:sand":4,"minecraft:dark_oak_fence":2,"minecraft:emerald":42,"minecraft:rail":23,"minecraft:crossbow":7,"minecraft:lever":1,"minecraft:filled_map":2,"minecraft:minecart":2,"minecraft:light_gray_wool":2,"minecraft:crying_obsidian":1,"minecraft:diamond_pickaxe":3,"minecraft:string":4,"minecraft:iron_leggings":1,"minecraft:polished_blackstone_bricks":1,"minecraft:crimson_nylium":49,"minecraft:stick":64,"minecraft:arrow":2,"minecraft:crimson_fungus":5,"minecraft:carrot":9,"minecraft:spruce_log":178,"minecraft:deepslate":37,"minecraft:gunpowder":3,"minecraft:bread":5,"minecraft:blast_furnace":8,"minecraft:netherrack":434,"minecraft:mutton":6,"minecraft:fletching_table":14,"minecraft:dark_oak_log":3,"minecraft:baked_potato":6,"minecraft:polished_blackstone_brick_stairs":1},"minecraft:used":{"minecraft:repeater":11,"minecraft:observer":2,"minecraft:deepslate":8,"minecraft:white_banner":7,"minecraft:diamond_sword":633,"minecraft:cherry_planks":11,"minecraft:wheat_seeds":27,"minecraft:glass_bottle":3,"minecraft:diamond_pickaxe":4357,"minecraft:bookshelf":12,"minecraft:glass":8,"minecraft:crossbow":1,"minecraft:dark_oak_fence":4,"minecraft:magma_block":1,"minecraft:blast_furnace":23,"minecraft:tuff":66,"minecraft:minecart":3,"minecraft:brewing_stand":4,"minecraft:copper_ore":40,"minecraft:cherry_boat":3,"minecraft:ominous_bottle":1,"minecraft:redstone":22,"minecraft:spruce_door":1,"minecraft:diamond_leggings":2,"minecraft:coal_ore":24,"minecraft:crafter":6,"minecraft:lapis_ore":4,"minecraft:crimson_roots":1,"minecraft:diamond_chestplate":3,"minecraft:stone":59,"minecraft:hopper":10,"minecraft:grindstone":6,"minecraft:diamond_axe":173,"minecraft:nether_gold_ore":20,"minecraft:crafting_table":1,"minecraft:cherry_slab":3,"minecraft:poppy":2,"minecraft:iron_chestplate":1,"minecraft:white_bed":3,"minecraft:bow":541,"minecraft:diamond_boots":2,"minecraft:cherry_button":1,"minecraft:baked_potato":143,"minecraft:iron_leggings":1,"minecraft:netherrack":665,"minecraft:diamond_shovel":172,"minecraft:deepslate_diamond_ore":56,"minecraft:nether_quartz_ore":32,"minecraft:pumpkin":1,"minecraft:water_bucket":12,"minecraft:bone_meal":197,"minecraft:deepslate_lapis_ore":5,"minecraft:fletching_table":8,"minecraft:anvil":4,"minecraft:torch":30,"minecraft:dirt":415,"minecraft:obsidian":8,"minecraft:deepslate_redstone_ore":49,"minecraft:spruce_button":1,"minecraft:gravel":10,"minecraft:crimson_stairs":2,"minecraft:rail":37,"minecraft:deepslate_gold_ore":42,"minecraft:comparator":4,"minecraft:shears":1,"minecraft:flint_and_steel":3,"minecraft:redstone_torch":4,"minecraft:bucket":15,"minecraft:chest":17,"minecraft:carved_pumpkin":1,"minecraft:cauldron":2,"minecraft:deepslate_iron_ore":4,"minecraft:oak_planks":1,"minecraft:spruce_sapling":269,"minecraft:iron_ore":6,"minecraft:ender_pearl":4},"minecraft:killed":{"minecraft:pillager":129,"minecraft:stray":1,"minecraft:skeleton":21,"minecraft:iron_golem":6,"minecraft:witch":2,"minecraft:piglin":5,"minecraft:villager":6,"minecraft:vindicator":2,"minecraft:spider":4,"minecraft:salmon":2,"minecraft:zombie":39,"minecraft:trader_llama":1,"minecraft:creeper":14,"minecraft:zombie_villager":3,"minecraft:enderman":3,"minecraft:hoglin":16,"minecraft:sheep":4,"minecraft:drowned":1,"minecraft:cow":2},"minecraft:crafted":{"minecraft:diamond_boots":2,"minecraft:stick":31679,"minecraft:minecart":5,"minecraft:diamond_axe":1,"minecraft:iron_block":12,"minecraft:diamond_pickaxe":2,"minecraft:chest":14,"minecraft:bookshelf":11,"minecraft:stone_slab":6,"minecraft:air":0,"minecraft:ender_pearl":2,"minecraft:bow":2,"minecraft:repeater":2,"minecraft:redstone":10,"minecraft:bone_meal":171,"minecraft:glass_bottle":3,"minecraft:diamond_shovel":1,"minecraft:crafter":3,"minecraft:glass":121,"minecraft:blast_furnace":7,"minecraft:redstone_torch":10,"minecraft:lapis_lazuli":11,"minecraft:oak_planks":16,"minecraft:sugar":6,"minecraft:comparator":3,"minecraft:hopper":3,"minecraft:spruce_door":3,"minecraft:anvil":4,"minecraft:smooth_stone":21,"minecraft:charcoal":2,"minecraft:glowstone":18,"minecraft:fletching_table":9,"minecraft:fermented_spider_eye":6,"minecraft:diamond_chestplate":2,"minecraft:emerald":1110,"minecraft:furnace":6,"minecraft:grindstone":1,"minecraft:diamond_helmet":2,"minecraft:crafting_table":4,"minecraft:experience_bottle":12,"minecraft:diamond_leggings":2,"minecraft:torch":20,"minecraft:white_bed":1,"minecraft:enchanted_book":24,"minecraft:baked_potato":115,"minecraft:dropper":3,"minecraft:observer":2,"minecraft:spruce_planks":6636,"minecraft:spruce_button":1},"minecraft:picked_up":{"minecraft:sweet_berries":19,"minecraft:brewing_stand":3,"minecraft:shears":7,"minecraft:minecart":25,"minecraft:cobblestone":21,"minecraft:glass":12,"minecraft:flint":11,"minecraft:redstone":317,"minecraft:bone":31,"minecraft:diamond_shovel":8,"minecraft:diamond":129,"minecraft:white_banner":25,"minecraft:emerald":285,"minecraft:deepslate_diamond_ore":56,"minecraft:crimson_roots":14,"minecraft:deepslate_iron_ore":4,"minecraft:sugar":4,"minecraft:book":48,"minecraft:crimson_fungus":7,"minecraft:cherry_button":1,"minecraft:gold_block":1,"minecraft:nether_quartz_ore":9,"minecraft:bow":6,"minecraft:arrow":51,"minecraft:iron_ingot":315,"minecraft:crossbow":13,"minecraft:polished_blackstone_brick_stairs":1,"minecraft:raw_gold":95,"minecraft:mutton":6,"minecraft:diamond_leggings":5,"minecraft:crying_obsidian":2,"minecraft:spruce_planks":2334,"minecraft:polished_blackstone_bricks":1,"minecraft:dirt":48,"minecraft:rail":53,"minecraft:crimson_nylium":146,"minecraft:diamond_helmet":3,"minecraft:iron_shovel":1,"minecraft:crimson_stem":6,"minecraft:torch":15,"minecraft:diamond_pickaxe":16,"minecraft:cherry_log":2,"minecraft:bread":5,"minecraft:spruce_log":5347,"minecraft:oak_stairs":44,"minecraft:coal":71,"minecraft:oak_log":4,"minecraft:birch_planks":2,"minecraft:sand":97,"minecraft:iron_ore":6,"minecraft:wheat_seeds":80,"minecraft:weeping_vines":4,"minecraft:quartz":70,"minecraft:diamond_sword":7,"minecraft:hopper":7,"minecraft:poppy":11,"minecraft:white_wool":3,"minecraft:fletching_table":13,"minecraft:blast_furnace":24,"minecraft:ender_pearl":18,"minecraft:string":9,"minecraft:obsidian":11,"minecraft:amethyst_shard":4,"minecraft:filled_map":1,"minecraft:comparator":3,"minecraft:coal_ore":24,"minecraft:diamond_axe":7,"minecraft:carrot":9,"minecraft:spruce_sapling":374,"minecraft:glowstone":25,"minecraft:white_bed":2,"minecraft:leather":5,"minecraft:gold_nugget":193,"minecraft:lead":3,"minecraft:brown_mushroom":18,"minecraft:water_bucket":6,"minecraft:baked_potato":168,"minecraft:glow_ink_sac":7,"minecraft:carved_pumpkin":33,"minecraft:porkchop":38,"minecraft:copper_ore":40,"minecraft:deepslate_lapis_ore":5,"minecraft:stick":349,"minecraft:dark_oak_fence":6,"minecraft:redstone_torch":4,"minecraft:deepslate_redstone_ore":49,"minecraft:diamond_boots":4,"minecraft:crimson_stairs":2,"minecraft:deepslate":493,"minecraft:repeater":10,"minecraft:cauldron":2,"minecraft:grindstone":4,"minecraft:raw_iron":24,"minecraft:diamond_chestplate":7,"minecraft:lapis_ore":4,"minecraft:glowstone_dust":1,"minecraft:pumpkin_seeds":40,"minecraft:amethyst_block":32,"minecraft:wheat":27,"minecraft:cherry_boat":3,"minecraft:spruce_door":1,"minecraft:cherry_planks":54,"minecraft:cherry_slab":1,"minecraft:gunpowder":16,"minecraft:chest":6,"minecraft:lectern":1,"minecraft:nether_gold_ore":10,"minecraft:netherrack":2409,"minecraft:magma_block":35,"minecraft:lever":1,"minecraft:stone":136,"minecraft:gravel":19,"minecraft:light_gray_wool":2,"minecraft:amethyst_cluster":2,"minecraft:tuff":66,"minecraft:deepslate_gold_ore":42,"minecraft:lapis_lazuli":119,"minecraft:pumpkin":1,"minecraft:spider_eye":1,"minecraft:dark_oak_log":3,"minecraft:tipped_arrow":1,"minecraft:ominous_bottle":13,"minecraft:cherry_sapling":2,"minecraft:oak_planks":74,"minecraft:flint_and_steel":6,"minecraft:raw_copper":326,"minecraft:beef":5,"minecraft:rotten_flesh":62,"minecraft:ancient_debris":1,"minecraft:crafter":4,"minecraft:calcite":3},"minecraft:broken":{"minecraft:diamond_boots":1}},"DataVersion":4440}